flask_switch.py
setup.py
Flask_Switch.egg-info/PKG-INFO
Flask_Switch.egg-info/SOURCES.txt
Flask_Switch.egg-info/dependency_links.txt
Flask_Switch.egg-info/not-zip-safe
Flask_Switch.egg-info/requires.txt
Flask_Switch.egg-info/top_level.txt