Metadata-Version: 1.1
Name: Flask-Switch
Version: 1.1
Summary: Automatic registration for Flask blueprints
Home-page: UNKNOWN
Author: apecnascimento
Author-email: apecnascimento@gmail.com
License: MIT
Platform: any
Classifier: Environment :: Web Environment
Classifier: Intended Audience :: Developers
Classifier: License :: OSI Approved :: MIT License
Classifier: Operating System :: OS Independent
Classifier: Programming Language :: Python
Classifier: Topic :: Internet :: WWW/HTTP :: Dynamic Content
Classifier: Topic :: Software Development :: Libraries :: Python Modules
